nautobot_capacity_metrics/__init__.py
nautobot_capacity_metrics/api/__init__.py
nautobot_capacity_metrics/api/urls.py
nautobot_capacity_metrics/api/views.py
nautobot_capacity_metrics/app-config-schema.json
nautobot_capacity_metrics/metrics.py
nautobot_capacity_metrics/static/nautobot_capacity_metrics/docs/404.html
nautobot_capacity_metrics/static/nautobot_capacity_metrics/docs/admin/compatibility_matrix.html
nautobot_capacity_metrics/static/nautobot_capacity_metrics/docs/admin/install.html
nautobot_capacity_metrics/static/nautobot_capacity_metrics/docs/admin/release_notes/index.html
nautobot_capacity_metrics/static/nautobot_capacity_metrics/docs/admin/release_notes/version_1.0.html
nautobot_capacity_metrics/static/nautobot_capacity_metrics/docs/admin/release_notes/version_1.1.html
nautobot_capacity_metrics/static/nautobot_capacity_metrics/docs/admin/release_notes/version_2.0.html
nautobot_capacity_metrics/static/nautobot_capacity_metrics/docs/admin/release_notes/version_2.1.html
nautobot_capacity_metrics/static/nautobot_capacity_metrics/docs/admin/release_notes/version_3.0.html
nautobot_capacity_metrics/static/nautobot_capacity_metrics/docs/admin/release_notes/version_3.1.html
nautobot_capacity_metrics/static/nautobot_capacity_metrics/docs/admin/release_notes/version_4.0.html
nautobot_capacity_metrics/static/nautobot_capacity_metrics/docs/admin/uninstall.html
nautobot_capacity_metrics/static/nautobot_capacity_metrics/docs/admin/upgrade.html
nautobot_capacity_metrics/static/nautobot_capacity_metrics/docs/assets/_mkdocstrings.css
nautobot_capacity_metrics/static/nautobot_capacity_metrics/docs/assets/extra.css
nautobot_capacity_metrics/static/nautobot_capacity_metrics/docs/assets/favicon.ico
nautobot_capacity_metrics/static/nautobot_capacity_metrics/docs/assets/images/favicon.png
nautobot_capacity_metrics/static/nautobot_capacity_metrics/docs/assets/javascripts/bundle.60a45f97.min.js
nautobot_capacity_metrics-4.0.0.dist-info/LICENSE
nautobot_capacity_metrics-4.0.0.dist-info/METADATA
nautobot_capacity_metrics-4.0.0.dist-info/WHEEL
nautobot_capacity_metrics-4.0.0.dist-info/RECORD
